phylostan/__init__.py
phylostan/generate_script.py
phylostan/phylostan (Kai's conflicted copy 2021-12-05).py
phylostan/phylostan.py
phylostan/utils.py
phylostan-1.0.5.post1.dist-info/LICENSE
phylostan-1.0.5.post1.dist-info/METADATA
phylostan-1.0.5.post1.dist-info/WHEEL
phylostan-1.0.5.post1.dist-info/entry_points.txt
phylostan-1.0.5.post1.dist-info/top_level.txt
phylostan-1.0.5.post1.dist-info/RECORD
