Metadata-Version: 2.1
Name: phylostan
Version: 1.0.5.post1
Summary: Phylogenetic inference with Stan
Home-page: https://github.com/4ment/phylostan
Author: Mathieu Fourment
Author-email: mathieu.fourment@uts.edu.au
License: GPL3
Keywords: phylogenetics,variational,HMC,Bayes,Stan
Platform: UNKNOWN
Classifier: Intended Audience :: Science/Research
Classifier: License :: OSI Approved :: GNU General Public License v3 (GPLv3)
Classifier: Operating System :: OS Independent
Classifier: Programming Language :: Python :: 3.6
Classifier: Programming Language :: Python :: 3.7
Classifier: Programming Language :: Python :: 3.8
Classifier: Programming Language :: Python :: 3.9
Classifier: Topic :: Scientific/Engineering :: Bio-Informatics
Requires-Python: >=3.6
Requires-Dist: DendroPy
Requires-Dist: numpy (>=1.7)
Requires-Dist: pystan (<3,>=2.19)
Provides-Extra: dev
Requires-Dist: black ; extra == 'dev'
Requires-Dist: flake8 ; extra == 'dev'
Requires-Dist: isort ; extra == 'dev'
Requires-Dist: pylint ; extra == 'dev'
Provides-Extra: test
Requires-Dist: pytest ; extra == 'test'
